paradigms/__init__.py
paradigms/core.py
paradigms/py.typed
paradigms/stdlib.py
paradigms-0.0.0.dev2.dist-info/METADATA
paradigms-0.0.0.dev2.dist-info/WHEEL
paradigms-0.0.0.dev2.dist-info/licenses/LICENSE.txt
paradigms-0.0.0.dev2.dist-info/RECORD
