Metadata-Version: 2.4
Name: paradigms
Version: 0.0.0.dev2
Summary: Different execution paradigms
Author-email: Chris Withers <chris@withers.org>
License-File: LICENSE.txt
Requires-Python: >=3.12
